cupy/__init__.py
cupy/_environment.py
cupy/_util.cpython-39-x86_64-linux-gnu.so
cupy/_version.py
cupy/cublas.py
cupy/cusolver.cpython-39-x86_64-linux-gnu.so
cupy/cusparse.py
cupy/.data/_wheel.json
cupy/_binary/__init__.py
cupy/_binary/elementwise.py
cupy/_binary/packing.py
cupy/_core/__init__.py
cupy/_core/_accelerator.cpython-39-x86_64-linux-gnu.so
cupy/_core/_carray.cpython-39-x86_64-linux-gnu.so
cupy/_core/_codeblock.py
cupy/_core/_cub_reduction.cpython-39-x86_64-linux-gnu.so
cupy/_core/_dtype.cpython-39-x86_64-linux-gnu.so
cupy/_core/_fusion_interface.py
cupy/_core/_fusion_kernel.cpython-39-x86_64-linux-gnu.so
cupy/_core/_fusion_op.py
cupy/_core/_fusion_optimization.py
cupy/_core/_fusion_thread_local.cpython-39-x86_64-linux-gnu.so
cupy/_core/_fusion_trace.cpython-39-x86_64-linux-gnu.so
cupy/_core/_fusion_variable.cpython-39-x86_64-linux-gnu.so
cupy/_core/_gufuncs.py
cupy/_core/_kernel.cpython-39-x86_64-linux-gnu.so
cupy/_core/_memory_range.cpython-39-x86_64-linux-gnu.so
cupy/_core/_optimize_config.cpython-39-x86_64-linux-gnu.so
cupy/_core/_reduction.cpython-39-x86_64-linux-gnu.so
cupy/_core/_routines_binary.cpython-39-x86_64-linux-gnu.so
cupy/_core/_routines_indexing.cpython-39-x86_64-linux-gnu.so
cupy/_core/_routines_linalg.cpython-39-x86_64-linux-gnu.so
cupy/_core/_routines_logic.cpython-39-x86_64-linux-gnu.so
cupy/_core/_routines_manipulation.cpython-39-x86_64-linux-gnu.so
cupy/_core/_routines_math.cpython-39-x86_64-linux-gnu.so
cupy/_core/_routines_sorting.cpython-39-x86_64-linux-gnu.so
cupy/_core/_routines_statistics.cpython-39-x86_64-linux-gnu.so
cupy/_core/_scalar.cpython-39-x86_64-linux-gnu.so
cupy/_core/_ufuncs.py
cupy/_core/core.cpython-39-x86_64-linux-gnu.so
cupy/_core/dlpack.cpython-39-x86_64-linux-gnu.so
cupy/_core/flags.cpython-39-x86_64-linux-gnu.so
cupy/_core/fusion.cpython-39-x86_64-linux-gnu.so
cupy/_core/internal.cpython-39-x86_64-linux-gnu.so
cupy/_core/new_fusion.cpython-39-x86_64-linux-gnu.so
cupy/_core/raw.cpython-39-x86_64-linux-gnu.so
cupy_rocm_4_2-10.6.0.dist-info/METADATA
cupy_rocm_4_2-10.6.0.dist-info/WHEEL
cupy_rocm_4_2-10.6.0.dist-info/license.rst
cupy_rocm_4_2-10.6.0.dist-info/top_level.txt
cupy_rocm_4_2-10.6.0.dist-info/RECORD
